corruptor/__init__.py
corruptor-0.0.0.dist-info/LICENSE
corruptor-0.0.0.dist-info/METADATA
corruptor-0.0.0.dist-info/WHEEL
corruptor-0.0.0.dist-info/top_level.txt
corruptor-0.0.0.dist-info/RECORD
