Metadata-Version: 2.1
Name: corruptor
Version: 0.0.0
Summary: Scientific text noise corruption for language model pretraining
Home-page: https://github.com/jaketae/corruptor
Author: Jake Tae
Author-email: jaesungtae@gmail.com
License: UNKNOWN
Platform: UNKNOWN
Classifier: Programming Language :: Python :: 3
Classifier: Programming Language :: Python :: 3.6
Classifier: Programming Language :: Python :: 3.7
Classifier: Programming Language :: Python :: 3.8
Classifier: License :: OSI Approved :: MIT License
Classifier: Operating System :: OS Independent
Requires-Python: >=3.6
